setup.py
statplot/Binomialdistribution.py
statplot/Gaussiandistribution.py
statplot/Generaldistribution.py
statplot/__init__.py
statplot.egg-info/PKG-INFO
statplot.egg-info/SOURCES.txt
statplot.egg-info/dependency_links.txt
statplot.egg-info/not-zip-safe
statplot.egg-info/top_level.txt