Metadata-Version: 1.0
Name: statplot
Version: 0.1
Summary: Gaussian and Binomial distributions
Home-page: UNKNOWN
Author: ['Godspower Onyenanu']
Author-email: UNKNOWN
License: UNKNOWN
Platform: UNKNOWN
